aerende/__init__.py
aerende/__main__.py
aerende/cli.py
aerende/configuration.py
aerende/controller.py
aerende/interface.py
aerende/models.py
aerende-0.2.0.dist-info/DESCRIPTION.rst
aerende-0.2.0.dist-info/METADATA
aerende-0.2.0.dist-info/RECORD
aerende-0.2.0.dist-info/WHEEL
aerende-0.2.0.dist-info/entry_points.txt
aerende-0.2.0.dist-info/metadata.json
aerende-0.2.0.dist-info/top_level.txt
